{
  "id": "hero",
  "type": "SharedSlice",
  "name": "ArticleHeroComponent",
  "description": "Hero",
  "variations": [
    {
      "id": "default",
      "name": "Default",
      "docURL": "...",
      "version": "initial",
      "description": "Default",
      "imageUrl": "",
      "primary": {
        "image": {
          "type": "Image",
          "config": { "label": "image", "constraint": {}, "thumbnails": [] }
        },
        "title": {
          "type": "StructuredText",
          "config": {
            "label": "title",
            "placeholder": "",
            "allowTargetBlank": false,
            "single": "heading1"
          }
        }
      },
      "items": {}
    }
  ]
}
